{
  "type": "MaxHistoryTrackerFeaturizer",
  "state_featurizer": {
    "action_texts": [],
    "entity_tag_specs": [],
    "feature_states": {
      "intent": {
        "affirm": 0,
        "ask_for_help": 1,
        "ask_for_weather": 2,
        "ask_relaxation": 3,
        "back": 4,
        "bot_challenge": 5,
        "deny": 6,
        "express_loneliness": 7,
        "express_stress": 8,
        "goodbye": 9,
        "greet": 10,
        "mood_great": 11,
        "mood_unhappy": 12,
        "need_motivation": 13,
        "need_relaxation_tip": 14,
        "nlu_fallback": 15,
        "out_of_scope": 16,
        "praise_bot": 17,
        "propose_movie": 18,
        "propose_music": 19,
        "propose_yoga": 20,
        "provide_feedback": 21,
        "restart": 22,
        "session_start": 23,
        "small_talk": 24,
        "talk_about_sleep": 25
      },
      "action_name": {
        "action_listen": 0,
        "action_restart": 1,
        "action_session_start": 2,
        "action_default_fallback": 3,
        "action_deactivate_loop": 4,
        "action_revert_fallback_events": 5,
        "action_default_ask_affirmation": 6,
        "action_default_ask_rephrase": 7,
        "action_two_stage_fallback": 8,
        "action_unlikely_intent": 9,
        "action_back": 10,
        "...": 11,
        "action_extract_slots": 12,
        "utter_cheer_up": 13,
        "utter_did_that_help": 14,
        "utter_express_loneliness": 15,
        "utter_express_stress": 16,
        "utter_goodbye": 17,
        "utter_greet": 18,
        "utter_happy": 19,
        "utter_iamabot": 20,
        "utter_movie_suggestion": 21,
        "utter_music_suggestion": 22,
        "utter_need_motivation": 23,
        "utter_need_relaxation_tip": 24,
        "utter_provide_help": 25,
        "utter_provide_weather": 26,
        "utter_relaxation_tip": 27,
        "utter_sleep_tip": 28,
        "utter_small_talk": 29,
        "utter_talk_about_sleep": 30,
        "utter_thank_you_for_feedback": 31,
        "utter_thank_you_for_praise": 32,
        "utter_well_being_suggestion": 33,
        "utter_yoga_suggestion": 34
      },
      "entities": {},
      "slots": {},
      "active_loop": {}
    }
  },
  "remove_duplicates": true,
  "max_history": 5
}